{"_type":"export","__export_format":4,"__export_date":"2023-11-20T23:44:04.995Z","__export_source":"insomnia.desktop.app:v2023.4.0","resources":[{"_id":"req_4bcb8af786d7472ab5d52836aab8ff0e","parentId":"fld_7b75b2c1ca974e63acccf75e54ac00e7","modified":1700519635221,"created":1700519607205,"url":"localhost:3002/balance","name":"getBalance","description":"","method":"GET","body":{},"parameters":[],"headers":[],"authentication":{},"metaSortKey":-1700519607205,"isPrivate":false,"settingStoreCookies":true,"settingSendCookies":true,"settingDisableRenderRequestBody":false,"settingEncodeUrl":true,"settingRebuildPath":true,"settingFollowRedirects":"global","_type":"request"},{"_id":"fld_7b75b2c1ca974e63acccf75e54ac00e7","parentId":"wrk_0a4ba1e16d0b42cb84e2a713ada35c0f","modified":1700519605557,"created":1700519605557,"name":"Balance","description":"","environment":{},"environmentPropertyOrder":null,"metaSortKey":-1700519605557,"_type":"request_group"},{"_id":"wrk_0a4ba1e16d0b42cb84e2a713ada35c0f","parentId":null,"modified":1700519694214,"created":1700519180005,"name":"Api pagamentos","description":"","scope":"design","_type":"workspace"},{"_id":"req_73947029069049799c68025a0f615b28","parentId":"fld_91611730c6984d15a851ea76082d0ff0","modified":1700522248491,"created":1700522225573,"url":"localhost:3002/payables/sum","name":"getSum","description":"","method":"GET","body":{},"parameters":[],"headers":[],"authentication":{},"metaSortKey":-1700522225573,"isPrivate":false,"settingStoreCookies":true,"settingSendCookies":true,"settingDisableRenderRequestBody":false,"settingEncodeUrl":true,"settingRebuildPath":true,"settingFollowRedirects":"global","_type":"request"},{"_id":"fld_91611730c6984d15a851ea76082d0ff0","parentId":"wrk_0a4ba1e16d0b42cb84e2a713ada35c0f","modified":1700519347852,"created":1700519347852,"name":"Payables","description":"","environment":{},"environmentPropertyOrder":null,"metaSortKey":-1700519347852,"_type":"request_group"},{"_id":"req_2f67d7e1f1114aafb40abdbbf6b33e38","parentId":"fld_91611730c6984d15a851ea76082d0ff0","modified":1700519657884,"created":1700519559700,"url":"localhost:3002/payables","name":"getAll","description":"","method":"GET","body":{},"parameters":[],"headers":[],"authentication":{},"metaSortKey":-1700519559700,"isPrivate":false,"settingStoreCookies":true,"settingSendCookies":true,"settingDisableRenderRequestBody":false,"settingEncodeUrl":true,"settingRebuildPath":true,"settingFollowRedirects":"global","_type":"request"},{"_id":"req_fbb0121edde94ee6983f01c6b9b681b2","parentId":"fld_91611730c6984d15a851ea76082d0ff0","modified":1700521941047,"created":1700519350109,"url":"localhost:3002/payables","name":"PayablesController.create","description":"","method":"POST","body":{"mimeType":"application/json","text":"{\n  \"transactionId\": 1,\n  \"status\": \"paid\",\n  \"paymentDate\": \"2023-01-01\",\n  \"amount\": 100.00\n}"},"parameters":[],"headers":[{"name":"Content-Type","value":"application/json"}],"authentication":{},"metaSortKey":-1700519350109,"isPrivate":false,"settingStoreCookies":true,"settingSendCookies":true,"settingDisableRenderRequestBody":false,"settingEncodeUrl":true,"settingRebuildPath":true,"settingFollowRedirects":"global","_type":"request"},{"_id":"req_a959bf32685d404dacb861310f3786ae","parentId":"fld_cb9b77b4b85d4ce59a95bef28eb058b6","modified":1700519302526,"created":1700519288003,"url":"localhost:3002/transactions","name":"transactionsController.getAll","description":"","method":"GET","body":{},"parameters":[],"headers":[],"authentication":{},"metaSortKey":-1700519288003,"isPrivate":false,"settingStoreCookies":true,"settingSendCookies":true,"settingDisableRenderRequestBody":false,"settingEncodeUrl":true,"settingRebuildPath":true,"settingFollowRedirects":"global","_type":"request"},{"_id":"fld_cb9b77b4b85d4ce59a95bef28eb058b6","parentId":"wrk_0a4ba1e16d0b42cb84e2a713ada35c0f","modified":1700519190956,"created":1700519190956,"name":"Transaction","description":"","environment":{},"environmentPropertyOrder":null,"metaSortKey":-1700519190956,"_type":"request_group"},{"_id":"req_980cd8511d60442f811b21924de8948c","parentId":"fld_cb9b77b4b85d4ce59a95bef28eb058b6","modified":1700519259781,"created":1700519193700,"url":"localhost:3002/transactions","name":"transactionsController.create","description":"","method":"POST","body":{"mimeType":"application/json","text":"{\n  \"amount\": 100.00,\n  \"description\": \"Descrição da transação\",\n  \"paymentMethod\": \"debit_card\",\n  \"cardNumber\": \"1234567812345678\",\n  \"cardHolderName\": \"Nome do Titular\",\n  \"cardExpirationDate\": \"2023-12-31\",\n  \"cardVerificationCode\": \"123\"\n}"},"parameters":[],"headers":[{"name":"Content-Type","value":"application/json"}],"authentication":{},"metaSortKey":-1700519193700,"isPrivate":false,"settingStoreCookies":true,"settingSendCookies":true,"settingDisableRenderRequestBody":false,"settingEncodeUrl":true,"settingRebuildPath":true,"settingFollowRedirects":"global","_type":"request"},{"_id":"env_4d2723a1074a8ee66d2c17b921db800df7430757","parentId":"wrk_0a4ba1e16d0b42cb84e2a713ada35c0f","modified":1700519180009,"created":1700519180009,"name":"Base Environment","data":{},"dataPropertyOrder":null,"color":null,"isPrivate":false,"metaSortKey":1700519180009,"_type":"environment"},{"_id":"jar_4d2723a1074a8ee66d2c17b921db800df7430757","parentId":"wrk_0a4ba1e16d0b42cb84e2a713ada35c0f","modified":1700519180010,"created":1700519180010,"name":"Default Jar","cookies":[],"_type":"cookie_jar"},{"_id":"spc_b15eeac7a8fc4515a6be18635ad2293a","parentId":"wrk_0a4ba1e16d0b42cb84e2a713ada35c0f","modified":1700519694211,"created":1700519180007,"fileName":"Api pagamentos","contents":"","contentType":"yaml","_type":"api_spec"}]}